MANIFEST.in
README.rst
setup.py
ABBYY/__init__.py
ABBYY/cloud_ocr.py
ABBYY.egg-info/PKG-INFO
ABBYY.egg-info/SOURCES.txt
ABBYY.egg-info/dependency_links.txt
ABBYY.egg-info/requires.txt
ABBYY.egg-info/top_level.txt