Metadata-Version: 1.0
Name: ABBYY
Version: 0.2
Summary: ABBYY Cloud OCR API Wrapper.
Home-page: https://github.com/samueltc/ABBYY
Author: Samuel Cossette
Author-email: samueltc@gmail.com
License: LICENSE
Platform: UNKNOWN
